{
  "1": {
    "repoFullName": "saadeghi/daisyui",
    "totalPoints": 94037.5,
    "avatar": "https://avatars.githubusercontent.com/u/7342023?v=4"
  },
  "2": {
    "repoFullName": "saadeghi/design-systems",
    "totalPoints": 1899,
    "avatar": "https://avatars.githubusercontent.com/u/7342023?v=4"
  },
  "3": {
    "repoFullName": "saadeghi/browser-hack-sass-mixins",
    "totalPoints": 454,
    "avatar": "https://avatars.githubusercontent.com/u/7342023?v=4"
  },
  "4": {
    "repoFullName": "acetinkaya/ai_aLi",
    "totalPoints": 243,
    "avatar": "https://avatars.githubusercontent.com/u/35449105?v=4"
  },
  "5": {
    "repoFullName": "acetinkaya/DeepLearningTurkiye",
    "totalPoints": 198,
    "avatar": "https://avatars.githubusercontent.com/u/35449105?v=4"
  },
  "6": {
    "repoFullName": "necatiergin/C_PROGRAMLAMA_DILI_ODEVLERI",
    "totalPoints": 195,
    "avatar": "https://avatars.githubusercontent.com/u/46518309?v=4"
  },
  "7": {
    "repoFullName": "necatiergin/C_PLUS_PLUS_KURSU_ODEVLERI",
    "totalPoints": 190,
    "avatar": "https://avatars.githubusercontent.com/u/46518309?v=4"
  },
  "8": {
    "repoFullName": "necatiergin/C_LANGUAGE_COURSE_CODE",
    "totalPoints": 127.5,
    "avatar": "https://avatars.githubusercontent.com/u/46518309?v=4"
  },
  "9": {
    "repoFullName": "alerque/aur",
    "totalPoints": 121,
    "avatar": "https://avatars.githubusercontent.com/u/173595?v=4"
  },
  "10": {
    "repoFullName": "orhun/ApkServInject",
    "totalPoints": 101,
    "avatar": "https://avatars.githubusercontent.com/u/24392180?v=4"
  }
}